fake_cmd/__init__.py
fake_cmd/core/__init__.py
fake_cmd/core/client.py
fake_cmd/core/server.py
fake_cmd/utils/__init__.py
fake_cmd/utils/cmd_arg.py
fake_cmd/utils/comm.py
fake_cmd/utils/common.py
fake_cmd/utils/exception.py
fake_cmd/utils/file.py
fake_cmd/utils/logging.py
fake_cmd/utils/parallel.py
fake_cmd/utils/executors/__init__.py
fake_cmd/utils/executors/reader.py
fake_cmd/utils/executors/writer.py
fake_cmd-0.0.5.dist-info/METADATA
fake_cmd-0.0.5.dist-info/WHEEL
fake_cmd-0.0.5.dist-info/top_level.txt
fake_cmd-0.0.5.dist-info/RECORD
